[
    {
        "caption":"Перевозные бани",
        "text":"Lorem ipsum, dolor sit amet consectetur adipisicing elit. Maxime beatae laboriosam sequi culpa excepturi error!"
        
    },
    {
        "caption":"Дома из бруса",
        "text":"Lorem ipsum, dolor sit amet consectetur adipisicing elit. Maxime beatae laboriosam sequi culpa excepturi error!"
        
    },
    {
        "caption":"Бани из бруса",
        "text":"Lorem ipsum, dolor sit amet consectetur adipisicing elit. Maxime beatae laboriosam sequi culpa excepturi error!"
        
    },
    {
        "caption":"Срубы под усадку",
        "text":"Lorem ipsum, dolor sit amet consectetur adipisicing elit. Maxime beatae laboriosam sequi culpa excepturi error!"
        
    }
]